{
  "properties": [
    {
      "name": "dimon.lfs.url",
      "type": "java.lang.String",
      "description": "LFS client endpoint."
    },
    {
      "name": "dimon.lfs.login",
      "type": "java.lang.String",
      "description": "LFS client login."
    },
    {
      "name": "dimon.lfs.password",
      "type": "java.lang.String",
      "description": "LFS client password."
    },
    {
      "name": "dimon.lfs.port",
      "type": "java.lang.Integer",
      "description": "LFS client port."
    }
  ]
}